convertModel.py
convertToPaddleJSModel.py
fuseOps.py
optimizeModel.py
pruningModel.py
rnn.py
paddlejsconverter-1.0.8.dist-info/METADATA
paddlejsconverter-1.0.8.dist-info/WHEEL
paddlejsconverter-1.0.8.dist-info/entry_points.txt
paddlejsconverter-1.0.8.dist-info/top_level.txt
paddlejsconverter-1.0.8.dist-info/RECORD
