Metadata-Version: 2.1
Name: paddlejsconverter
Version: 1.0.8
Summary: Paddlejs model converter
Home-page: https://github.com/PaddlePaddle/Paddle.js
Author: paddlejs
Author-email: 382248373@qq.com
License: UNKNOWN
Platform: UNKNOWN
Classifier: Programming Language :: Python
Classifier: Programming Language :: Python :: 3
Classifier: License :: OSI Approved :: MIT License
Classifier: Operating System :: OS Independent
Requires-Python: >=3.6
Requires-Dist: paddlepaddle (>=2.0.0)
Requires-Dist: paddlejslite (>=0.0.2)
Requires-Dist: numpy
